xiaoxiongfjhasj/__init__.py
xiaoxiongfjhasj/oh_bear.py
xiaoxiongfjhasj-0.0.2.dist-info/METADATA
xiaoxiongfjhasj-0.0.2.dist-info/WHEEL
xiaoxiongfjhasj-0.0.2.dist-info/top_level.txt
xiaoxiongfjhasj-0.0.2.dist-info/RECORD
