Metadata-Version: 2.1
Name: xiaoxiongfjhasj
Version: 0.0.2
Summary: Oh Bear !
Author: ygg
Author-email: ygg@zut.edu.cn
Classifier: Programming Language :: Python :: 3
Classifier: License :: OSI Approved :: MIT License
Classifier: Operating System :: OS Independent
